README.md
setup.cfg
setup.py
circuit_webhook/__init__.py
circuit_webhook/circuit_webhook.py
circuit_webhook.egg-info/PKG-INFO
circuit_webhook.egg-info/SOURCES.txt
circuit_webhook.egg-info/dependency_links.txt
circuit_webhook.egg-info/top_level.txt