Metadata-Version: 2.1
Name: circuit-webhook
Version: 1.0.0
Summary: circuit-webhook is a python client library for Unify Circuit api         Incoming Webhooks on Python 3.6 and above.
Home-page: https://github.com/braam/unify/circuit-webhook-python
Author: braam
Author-email: braam.vanhavermaet+circuit@gmail.com
License: MIT
Keywords: circuit webhook python
Platform: UNKNOWN
Classifier: Development Status :: 5 - Production/Stable
Classifier: Programming Language :: Python
Classifier: Programming Language :: Python :: 3
Classifier: Programming Language :: Python :: 3.6
Classifier: Programming Language :: Python :: 3.7
Classifier: Programming Language :: Python :: 3.8
Classifier: Intended Audience :: Developers
Classifier: Topic :: Communications :: Chat
Classifier: Topic :: System :: Networking
Classifier: Topic :: Office/Business
Classifier: License :: OSI Approved :: MIT License
Requires-Python: >=3.6.0
